setup.cfg
setup.py
GeoLocation.egg-info/PKG-INFO
GeoLocation.egg-info/SOURCES.txt
GeoLocation.egg-info/dependency_links.txt
GeoLocation.egg-info/entry_points.txt
GeoLocation.egg-info/top_level.txt
GeoLocation.egg-info/zip-safe
geolocation/__init__.py
geolocation/us_states.py