Metadata-Version: 1.0
Name: GeoLocation
Version: 0.1.1dev
Summary: Geographical Locations
Home-page: UNKNOWN
Author: Eman Calso
Author-email: egcalso@gmail.com
License: LGPL
Platform: UNKNOWN
